setup.py
docs/conf.py
usgs/__init__.py
usgs_api.egg-info/PKG-INFO
usgs_api.egg-info/SOURCES.txt
usgs_api.egg-info/dependency_links.txt
usgs_api.egg-info/not-zip-safe
usgs_api.egg-info/top_level.txt