Metadata-Version: 1.0
Name: usgs-api
Version: 0.1.5a
Summary: A Python wrapper for the USGS National Water Information System JSON API
Home-page: https://bitbucket.org/UltraAyla/usgs-api
Author: Nick Santos
Author-email: python@nicksantos.com
License: Creative Commons Attribution Sharealike 3.0 Unported
Keywords: usgs,api,nwis,water,data,wrapper
Platform: UNKNOWN
